[{"lineNumber": 9, "col_offset": 0, "nodeName": "emulate_int", "type": "Callable[..., Any]"}, {"lineNumber": 14, "col_offset": 0, "nodeName": "quantize", "type": "Callable[..., Any]"}, {"lineNumber": 22, "col_offset": 0, "nodeName": "emulate_int8_histogram", "type": "Callable[..., Any]"}, {"lineNumber": 33, "col_offset": 0, "nodeName": "emulate_int8_channel", "type": "Callable[..., Any]"}, {"lineNumber": 46, "col_offset": 0, "nodeName": "emulate_int8_tensor", "type": "Callable[..., Any]"}, {"lineNumber": 10, "col_offset": 4, "nodeName": "q", "type": "Any"}, {"lineNumber": 16, "col_offset": 4, "nodeName": "max_val", "type": "Any"}, {"lineNumber": 11, "col_offset": 11, "nodeName": "q", "type": "Any"}, {"lineNumber": 11, "col_offset": 13, "nodeName": "w", "type": "Any"}, {"lineNumber": 19, "col_offset": 8, "nodeName": "scale", "type": "Any"}, {"lineNumber": 23, "col_offset": 7, "nodeName": "scale", "type": "Any"}, {"lineNumber": 24, "col_offset": 8, "nodeName": "obs", "type": "Any"}, {"lineNumber": 26, "col_offset": 8, "nodeName": "_", "type": "Any"}, {"lineNumber": 28, "col_offset": 8, "nodeName": "scale", "type": "Any"}, {"lineNumber": 29, "col_offset": 8, "nodeName": "zero_point", "type": "Any"}, {"lineNumber": 30, "col_offset": 54, "nodeName": "scale", "type": "Any"}, {"lineNumber": 30, "col_offset": 61, "nodeName": "zero_point", "type": "Any"}, {"lineNumber": 34, "col_offset": 7, "nodeName": "scale", "type": "Any"}, {"lineNumber": 39, "col_offset": 8, "nodeName": "_", "type": "Any"}, {"lineNumber": 41, "col_offset": 8, "nodeName": "scale", "type": "Any"}, {"lineNumber": 42, "col_offset": 8, "nodeName": "zero_point", "type": "Any"}, {"lineNumber": 43, "col_offset": 54, "nodeName": "scale", "type": "Any"}, {"lineNumber": 43, "col_offset": 61, "nodeName": "zero_point", "type": "Any"}, {"lineNumber": 47, "col_offset": 7, "nodeName": "scale", "type": "Any"}, {"lineNumber": 48, "col_offset": 8, "nodeName": "obs", "type": "Any"}, {"lineNumber": 50, "col_offset": 8, "nodeName": "_", "type": "Any"}, {"lineNumber": 52, "col_offset": 8, "nodeName": "scale", "type": "Any"}, {"lineNumber": 53, "col_offset": 8, "nodeName": "zero_point", "type": "Any"}, {"lineNumber": 54, "col_offset": 54, "nodeName": "scale", "type": "Any"}, {"lineNumber": 54, "col_offset": 61, "nodeName": "zero_point", "type": "Any"}, {"lineNumber": 10, "col_offset": 8, "nodeName": "globals", "type": "Callable[[], Dict[str, Any]]"}, {"lineNumber": 11, "col_offset": 22, "nodeName": "scale", "type": "Any"}, {"lineNumber": 11, "col_offset": 40, "nodeName": "zero_point", "type": "Any"}, {"lineNumber": 11, "col_offset": 57, "nodeName": "bits", "type": "Any"}, {"lineNumber": 16, "col_offset": 19, "nodeName": "bits", "type": "Any"}, {"lineNumber": 18, "col_offset": 71, "nodeName": "zero_point", "type": "Any"}, {"lineNumber": 24, "col_offset": 14, "nodeName": "HistogramObserver", "type": "Any"}, {"lineNumber": 25, "col_offset": 8, "nodeName": "to", "type": "Any"}, {"lineNumber": 26, "col_offset": 12, "nodeName": "obs", "type": "Any"}, {"lineNumber": 27, "col_offset": 8, "nodeName": "scale", "type": "Any"}, {"lineNumber": 27, "col_offset": 15, "nodeName": "zero_point", "type": "Any"}, {"lineNumber": 27, "col_offset": 28, "nodeName": "calculate_qparams", "type": "Any"}, {"lineNumber": 28, "col_offset": 16, "nodeName": "type_as", "type": "Any"}, {"lineNumber": 28, "col_offset": 37, "nodeName": "w", "type": "Any"}, {"lineNumber": 29, "col_offset": 21, "nodeName": "type_as", "type": "Any"}, {"lineNumber": 29, "col_offset": 47, "nodeName": "w", "type": "Any"}, {"lineNumber": 30, "col_offset": 11, "nodeName": "quantize", "type": "Callable[..., Any]"}, {"lineNumber": 30, "col_offset": 20, "nodeName": "w", "type": "Any"}, {"lineNumber": 30, "col_offset": 23, "nodeName": "scale", "type": "Any"}, {"lineNumber": 30, "col_offset": 30, "nodeName": "zero_point", "type": "Any"}, {"lineNumber": 35, "col_offset": 14, "nodeName": "PerChannelMinMaxObserver", "type": "Any"}, {"lineNumber": 38, "col_offset": 8, "nodeName": "to", "type": "Any"}, {"lineNumber": 39, "col_offset": 12, "nodeName": "obs", "type": "Any"}, {"lineNumber": 39, "col_offset": 16, "nodeName": "w", "type": "Any"}, {"lineNumber": 40, "col_offset": 8, "nodeName": "scale", "type": "Any"}, {"lineNumber": 40, "col_offset": 15, "nodeName": "zero_point", "type": "Any"}, {"lineNumber": 40, "col_offset": 27, "nodeName": "ch_axis", "type": "Any"}, {"lineNumber": 40, "col_offset": 37, "nodeName": "get_qparams", "type": "Any"}, {"lineNumber": 41, "col_offset": 16, "nodeName": "type_as", "type": "Any"}, {"lineNumber": 41, "col_offset": 37, "nodeName": "w", "type": "Any"}, {"lineNumber": 42, "col_offset": 21, "nodeName": "type_as", "type": "Any"}, {"lineNumber": 42, "col_offset": 47, "nodeName": "w", "type": "Any"}, {"lineNumber": 43, "col_offset": 11, "nodeName": "quantize", "type": "Callable[..., Any]"}, {"lineNumber": 43, "col_offset": 20, "nodeName": "w", "type": "Any"}, {"lineNumber": 43, "col_offset": 23, "nodeName": "scale", "type": "Any"}, {"lineNumber": 43, "col_offset": 30, "nodeName": "zero_point", "type": "Any"}, {"lineNumber": 48, "col_offset": 14, "nodeName": "MinMaxObserver", "type": "Any"}, {"lineNumber": 49, "col_offset": 8, "nodeName": "to", "type": "Any"}, {"lineNumber": 50, "col_offset": 12, "nodeName": "obs", "type": "Any"}, {"lineNumber": 50, "col_offset": 16, "nodeName": "w", "type": "Any"}, {"lineNumber": 51, "col_offset": 8, "nodeName": "scale", "type": "Any"}, {"lineNumber": 51, "col_offset": 15, "nodeName": "zero_point", "type": "Any"}, {"lineNumber": 51, "col_offset": 28, "nodeName": "calculate_qparams", "type": "Any"}, {"lineNumber": 52, "col_offset": 16, "nodeName": "type_as", "type": "Any"}, {"lineNumber": 52, "col_offset": 37, "nodeName": "w", "type": "Any"}, {"lineNumber": 53, "col_offset": 21, "nodeName": "type_as", "type": "Any"}, {"lineNumber": 53, "col_offset": 47, "nodeName": "w", "type": "Any"}, {"lineNumber": 54, "col_offset": 11, "nodeName": "quantize", "type": "Callable[..., Any]"}, {"lineNumber": 54, "col_offset": 20, "nodeName": "w", "type": "Any"}, {"lineNumber": 54, "col_offset": 23, "nodeName": "scale", "type": "Any"}, {"lineNumber": 54, "col_offset": 30, "nodeName": "zero_point", "type": "Any"}, {"lineNumber": 18, "col_offset": 8, "nodeName": "clamp", "type": "Any"}, {"lineNumber": 18, "col_offset": 60, "nodeName": "max_val", "type": "Any"}, {"lineNumber": 24, "col_offset": 14, "nodeName": "observer", "type": "Any"}, {"lineNumber": 25, "col_offset": 8, "nodeName": "obs", "type": "Any"}, {"lineNumber": 25, "col_offset": 22, "nodeName": "device", "type": "Any"}, {"lineNumber": 26, "col_offset": 16, "nodeName": "float", "type": "Any"}, {"lineNumber": 27, "col_offset": 28, "nodeName": "obs", "type": "Any"}, {"lineNumber": 30, "col_offset": 47, "nodeName": "bits", "type": "Any"}, {"lineNumber": 35, "col_offset": 14, "nodeName": "observer", "type": "Any"}, {"lineNumber": 36, "col_offset": 32, "nodeName": "per_channel_symmetric", "type": "Any"}, {"lineNumber": 38, "col_offset": 8, "nodeName": "obs", "type": "Any"}, {"lineNumber": 38, "col_offset": 22, "nodeName": "device", "type": "Any"}, {"lineNumber": 40, "col_offset": 37, "nodeName": "obs", "type": "Any"}, {"lineNumber": 43, "col_offset": 47, "nodeName": "bits", "type": "Any"}, {"lineNumber": 48, "col_offset": 14, "nodeName": "observer", "type": "Any"}, {"lineNumber": 49, "col_offset": 8, "nodeName": "obs", "type": "Any"}, {"lineNumber": 49, "col_offset": 22, "nodeName": "device", "type": "Any"}, {"lineNumber": 51, "col_offset": 28, "nodeName": "obs", "type": "Any"}, {"lineNumber": 54, "col_offset": 47, "nodeName": "bits", "type": "Any"}, {"lineNumber": 10, "col_offset": 34, "nodeName": "method", "type": "Any"}, {"lineNumber": 18, "col_offset": 8, "nodeName": "torch", "type": "Any"}, {"lineNumber": 18, "col_offset": 20, "nodeName": "round", "type": "Any"}, {"lineNumber": 24, "col_offset": 14, "nodeName": "quantization", "type": "Any"}, {"lineNumber": 25, "col_offset": 22, "nodeName": "w", "type": "Any"}, {"lineNumber": 26, "col_offset": 16, "nodeName": "w", "type": "Any"}, {"lineNumber": 28, "col_offset": 16, "nodeName": "cuda", "type": "Any"}, {"lineNumber": 29, "col_offset": 21, "nodeName": "cuda", "type": "Any"}, {"lineNumber": 35, "col_offset": 14, "nodeName": "quantization", "type": "Any"}, {"lineNumber": 36, "col_offset": 32, "nodeName": "torch", "type": "Any"}, {"lineNumber": 38, "col_offset": 22, "nodeName": "w", "type": "Any"}, {"lineNumber": 41, "col_offset": 16, "nodeName": "cuda", "type": "Any"}, {"lineNumber": 42, "col_offset": 21, "nodeName": "cuda", "type": "Any"}, {"lineNumber": 48, "col_offset": 14, "nodeName": "quantization", "type": "Any"}, {"lineNumber": 49, "col_offset": 22, "nodeName": "w", "type": "Any"}, {"lineNumber": 52, "col_offset": 16, "nodeName": "cuda", "type": "Any"}, {"lineNumber": 53, "col_offset": 21, "nodeName": "cuda", "type": "Any"}, {"lineNumber": 18, "col_offset": 20, "nodeName": "torch", "type": "Any"}, {"lineNumber": 18, "col_offset": 44, "nodeName": "zero_point", "type": "Any"}, {"lineNumber": 24, "col_offset": 14, "nodeName": "torch", "type": "Any"}, {"lineNumber": 28, "col_offset": 16, "nodeName": "scale", "type": "Any"}, {"lineNumber": 29, "col_offset": 21, "nodeName": "zero_point", "type": "Any"}, {"lineNumber": 35, "col_offset": 14, "nodeName": "torch", "type": "Any"}, {"lineNumber": 41, "col_offset": 16, "nodeName": "scale", "type": "Any"}, {"lineNumber": 42, "col_offset": 21, "nodeName": "zero_point", "type": "Any"}, {"lineNumber": 48, "col_offset": 14, "nodeName": "torch", "type": "Any"}, {"lineNumber": 52, "col_offset": 16, "nodeName": "scale", "type": "Any"}, {"lineNumber": 53, "col_offset": 21, "nodeName": "zero_point", "type": "Any"}, {"lineNumber": 18, "col_offset": 32, "nodeName": "w", "type": "Any"}, {"lineNumber": 18, "col_offset": 36, "nodeName": "scale", "type": "Any"}]