[{"lineNumber": 34, "col_offset": 23, "nodeName": "object", "type": "Type[object]"}, {"lineNumber": 50, "col_offset": 4, "nodeName": "config", "type": "Any"}, {"lineNumber": 50, "col_offset": 18, "nodeName": "config", "type": "Any"}, {"lineNumber": 51, "col_offset": 4, "nodeName": "mode", "type": "Any"}, {"lineNumber": 51, "col_offset": 16, "nodeName": "mode", "type": "Any"}, {"lineNumber": 52, "col_offset": 4, "nodeName": "train_inception", "type": "Any"}, {"lineNumber": 52, "col_offset": 27, "nodeName": "train_inception", "type": "Any"}, {"lineNumber": 55, "col_offset": 4, "nodeName": "reader", "type": "Any"}, {"lineNumber": 64, "col_offset": 4, "nodeName": "images", "type": "None"}, {"lineNumber": 67, "col_offset": 4, "nodeName": "input_seqs", "type": "None"}, {"lineNumber": 70, "col_offset": 4, "nodeName": "target_seqs", "type": "None"}, {"lineNumber": 73, "col_offset": 4, "nodeName": "input_mask", "type": "None"}, {"lineNumber": 76, "col_offset": 4, "nodeName": "image_embeddings", "type": "None"}, {"lineNumber": 79, "col_offset": 4, "nodeName": "seq_embeddings", "type": "None"}, {"lineNumber": 82, "col_offset": 4, "nodeName": "total_loss", "type": "None"}, {"lineNumber": 85, "col_offset": 4, "nodeName": "target_cross_entropy_losses", "type": "None"}, {"lineNumber": 88, "col_offset": 4, "nodeName": "target_cross_entropy_loss_weights", "type": "None"}, {"lineNumber": 91, "col_offset": 4, "nodeName": "inception_variables", "type": "List[nothing]"}, {"lineNumber": 94, "col_offset": 4, "nodeName": "init_fn", "type": "None"}, {"lineNumber": 97, "col_offset": 4, "nodeName": "global_step", "type": "None"}, {"lineNumber": 176, "col_offset": 4, "nodeName": "images", "type": "Any"}, {"lineNumber": 176, "col_offset": 18, "nodeName": "images", "type": "Any"}, {"lineNumber": 177, "col_offset": 4, "nodeName": "input_seqs", "type": "Any"}, {"lineNumber": 177, "col_offset": 22, "nodeName": "input_seqs", "type": "Any"}, {"lineNumber": 178, "col_offset": 4, "nodeName": "target_seqs", "type": "Any"}, {"lineNumber": 178, "col_offset": 23, "nodeName": "target_seqs", "type": "Any"}, {"lineNumber": 179, "col_offset": 4, "nodeName": "input_mask", "type": "Any"}, {"lineNumber": 179, "col_offset": 22, "nodeName": "input_mask", "type": "Any"}, {"lineNumber": 210, "col_offset": 4, "nodeName": "image_embeddings", "type": "Any"}, {"lineNumber": 210, "col_offset": 28, "nodeName": "image_embeddings", "type": "Any"}, {"lineNumber": 228, "col_offset": 4, "nodeName": "seq_embeddings", "type": "Any"}, {"lineNumber": 228, "col_offset": 26, "nodeName": "seq_embeddings", "type": "Any"}, {"lineNumber": 293, "col_offset": 4, "nodeName": "lstm_outputs", "type": "Any"}, {"lineNumber": 349, "col_offset": 4, "nodeName": "global_step", "type": "Any"}, {"lineNumber": 349, "col_offset": 23, "nodeName": "global_step", "type": "Any"}, {"lineNumber": 49, "col_offset": 11, "nodeName": "mode", "type": "Any"}, {"lineNumber": 50, "col_offset": 4, "nodeName": "self", "type": "ShowAndTellModel"}, {"lineNumber": 51, "col_offset": 4, "nodeName": "self", "type": "ShowAndTellModel"}, {"lineNumber": 52, "col_offset": 4, "nodeName": "self", "type": "ShowAndTellModel"}, {"lineNumber": 55, "col_offset": 4, "nodeName": "self", "type": "ShowAndTellModel"}, {"lineNumber": 55, "col_offset": 18, "nodeName": "TFRecordReader", "type": "Any"}, {"lineNumber": 59, "col_offset": 23, "nodeName": "random_uniform_initializer", "type": "Any"}, {"lineNumber": 64, "col_offset": 4, "nodeName": "self", "type": "ShowAndTellModel"}, {"lineNumber": 67, "col_offset": 4, "nodeName": "self", "type": "ShowAndTellModel"}, {"lineNumber": 70, "col_offset": 4, "nodeName": "self", "type": "ShowAndTellModel"}, {"lineNumber": 73, "col_offset": 4, "nodeName": "self", "type": "ShowAndTellModel"}, {"lineNumber": 76, "col_offset": 4, "nodeName": "self", "type": "ShowAndTellModel"}, {"lineNumber": 79, "col_offset": 4, "nodeName": "self", "type": "ShowAndTellModel"}, {"lineNumber": 82, "col_offset": 4, "nodeName": "self", "type": "ShowAndTellModel"}, {"lineNumber": 85, "col_offset": 4, "nodeName": "self", "type": "ShowAndTellModel"}, {"lineNumber": 88, "col_offset": 4, "nodeName": "self", "type": "ShowAndTellModel"}, {"lineNumber": 91, "col_offset": 4, "nodeName": "self", "type": "ShowAndTellModel"}, {"lineNumber": 94, "col_offset": 4, "nodeName": "self", "type": "ShowAndTellModel"}, {"lineNumber": 97, "col_offset": 4, "nodeName": "self", "type": "ShowAndTellModel"}, {"lineNumber": 101, "col_offset": 11, "nodeName": "mode", "type": "Any"}, {"lineNumber": 114, "col_offset": 11, "nodeName": "process_image", "type": "Any"}, {"lineNumber": 114, "col_offset": 42, "nodeName": "encoded_image", "type": "Any"}, {"lineNumber": 130, "col_offset": 7, "nodeName": "mode", "type": "Any"}, {"lineNumber": 132, "col_offset": 6, "nodeName": "image_feed", "type": "Any"}, {"lineNumber": 138, "col_offset": 6, "nodeName": "images", "type": "Any"}, {"lineNumber": 139, "col_offset": 6, "nodeName": "input_seqs", "type": "Any"}, {"lineNumber": 142, "col_offset": 6, "nodeName": "target_seqs", "type": "None"}, {"lineNumber": 143, "col_offset": 6, "nodeName": "input_mask", "type": "None"}, {"lineNumber": 158, "col_offset": 6, "nodeName": "images_and_captions", "type": "List[List[Any]]"}, {"lineNumber": 159, "col_offset": 10, "nodeName": "thread_id", "type": "int"}, {"lineNumber": 176, "col_offset": 4, "nodeName": "self", "type": "ShowAndTellModel"}, {"lineNumber": 177, "col_offset": 4, "nodeName": "self", "type": "ShowAndTellModel"}, {"lineNumber": 178, "col_offset": 4, "nodeName": "self", "type": "ShowAndTellModel"}, {"lineNumber": 179, "col_offset": 4, "nodeName": "self", "type": "ShowAndTellModel"}, {"lineNumber": 190, "col_offset": 23, "nodeName": "inception_v3", "type": "Any"}, {"lineNumber": 191, "col_offset": 8, "nodeName": "images", "type": "Any"}, {"lineNumber": 194, "col_offset": 31, "nodeName": "get_collection", "type": "Any"}, {"lineNumber": 195, "col_offset": 8, "nodeName": "GLOBAL_VARIABLES", "type": "Any"}, {"lineNumber": 198, "col_offset": 49, "nodeName": "scope", "type": "Any"}, {"lineNumber": 208, "col_offset": 4, "nodeName": "constant", "type": "Any"}, {"lineNumber": 208, "col_offset": 16, "nodeName": "embedding_size", "type": "Any"}, {"lineNumber": 210, "col_offset": 4, "nodeName": "self", "type": "ShowAndTellModel"}, {"lineNumber": 226, "col_offset": 6, "nodeName": "seq_embeddings", "type": "Any"}, {"lineNumber": 228, "col_offset": 4, "nodeName": "self", "type": "ShowAndTellModel"}, {"lineNumber": 247, "col_offset": 16, "nodeName": "BasicLSTMCell", "type": "Any"}, {"lineNumber": 249, "col_offset": 7, "nodeName": "mode", "type": "Any"}, {"lineNumber": 255, "col_offset": 68, "nodeName": "lstm_scope", "type": "Any"}, {"lineNumber": 293, "col_offset": 19, "nodeName": "reshape", "type": "Any"}, {"lineNumber": 293, "col_offset": 30, "nodeName": "lstm_outputs", "type": "Any"}, {"lineNumber": 295, "col_offset": 40, "nodeName": "logits_scope", "type": "Any"}, {"lineNumber": 303, "col_offset": 7, "nodeName": "mode", "type": "Any"}, {"lineNumber": 306, "col_offset": 6, "nodeName": "targets", "type": "Any"}, {"lineNumber": 307, "col_offset": 6, "nodeName": "weights", "type": "Any"}, {"lineNumber": 316, "col_offset": 6, "nodeName": "total_loss", "type": "Any"}, {"lineNumber": 321, "col_offset": 10, "nodeName": "var", "type": "Any"}, {"lineNumber": 324, "col_offset": 6, "nodeName": "total_loss", "type": "Any"}, {"lineNumber": 324, "col_offset": 24, "nodeName": "total_loss", "type": "Any"}, {"lineNumber": 325, "col_offset": 6, "nodeName": "target_cross_entropy_losses", "type": "Any"}, {"lineNumber": 325, "col_offset": 41, "nodeName": "losses", "type": "Any"}, {"lineNumber": 326, "col_offset": 6, "nodeName": "target_cross_entropy_loss_weights", "type": "Any"}, {"lineNumber": 326, "col_offset": 47, "nodeName": "weights", "type": "Any"}, {"lineNumber": 330, "col_offset": 7, "nodeName": "mode", "type": "Any"}, {"lineNumber": 332, "col_offset": 6, "nodeName": "saver", "type": "Any"}, {"lineNumber": 339, "col_offset": 6, "nodeName": "init_fn", "type": "Callable[[Any], Any]"}, {"lineNumber": 339, "col_offset": 21, "nodeName": "restore_fn", "type": "Callable[[Any], Any]"}, {"lineNumber": 343, "col_offset": 18, "nodeName": "Variable", "type": "Any"}, {"lineNumber": 349, "col_offset": 4, "nodeName": "self", "type": "ShowAndTellModel"}, {"lineNumber": 353, "col_offset": 4, "nodeName": "build_inputs", "type": "Callable[[], Any]"}, {"lineNumber": 354, "col_offset": 4, "nodeName": "build_image_embeddings", "type": "Callable[[], Any]"}, {"lineNumber": 355, "col_offset": 4, "nodeName": "build_seq_embeddings", "type": "Callable[[], Any]"}, {"lineNumber": 356, "col_offset": 4, "nodeName": "build_model", "type": "Callable[[], Any]"}, {"lineNumber": 357, "col_offset": 4, "nodeName": "setup_inception_initializer", "type": "Callable[[], Any]"}, {"lineNumber": 358, "col_offset": 4, "nodeName": "setup_global_step", "type": "Callable[[], Any]"}, {"lineNumber": 55, "col_offset": 18, "nodeName": "tf", "type": "Any"}, {"lineNumber": 59, "col_offset": 23, "nodeName": "tf", "type": "Any"}, {"lineNumber": 61, "col_offset": 15, "nodeName": "initializer_scale", "type": "Any"}, {"lineNumber": 101, "col_offset": 11, "nodeName": "self", "type": "ShowAndTellModel"}, {"lineNumber": 114, "col_offset": 11, "nodeName": "image_processing", "type": "Any"}, {"lineNumber": 116, "col_offset": 49, "nodeName": "image_height", "type": "Any"}, {"lineNumber": 117, "col_offset": 48, "nodeName": "image_width", "type": "Any"}, {"lineNumber": 118, "col_offset": 52, "nodeName": "thread_id", "type": "bool"}, {"lineNumber": 119, "col_offset": 55, "nodeName": "image_format", "type": "Any"}, {"lineNumber": 130, "col_offset": 7, "nodeName": "self", "type": "ShowAndTellModel"}, {"lineNumber": 132, "col_offset": 19, "nodeName": "placeholder", "type": "Any"}, {"lineNumber": 133, "col_offset": 19, "nodeName": "placeholder", "type": "Any"}, {"lineNumber": 138, "col_offset": 15, "nodeName": "expand_dims", "type": "Any"}, {"lineNumber": 139, "col_offset": 19, "nodeName": "expand_dims", "type": "Any"}, {"lineNumber": 139, "col_offset": 34, "nodeName": "input_feed", "type": "Any"}, {"lineNumber": 146, "col_offset": 20, "nodeName": "prefetch_input_data", "type": "Any"}, {"lineNumber": 147, "col_offset": 10, "nodeName": "reader", "type": "Any"}, {"lineNumber": 148, "col_offset": 10, "nodeName": "input_file_pattern", "type": "Any"}, {"lineNumber": 159, "col_offset": 23, "nodeName": "range", "type": "Type[range]"}, {"lineNumber": 159, "col_offset": 29, "nodeName": "num_preprocess_threads", "type": "Any"}, {"lineNumber": 160, "col_offset": 8, "nodeName": "serialized_sequence_example", "type": "Any"}, {"lineNumber": 165, "col_offset": 8, "nodeName": "image", "type": "Any"}, {"lineNumber": 170, "col_offset": 24, "nodeName": "batch_size", "type": "Any"}, {"lineNumber": 172, "col_offset": 10, "nodeName": "batch_with_dynamic_pad", "type": "Any"}, {"lineNumber": 172, "col_offset": 43, "nodeName": "images_and_captions", "type": "List[List[Any]]"}, {"lineNumber": 190, "col_offset": 23, "nodeName": "image_embedding", "type": "Any"}, {"lineNumber": 191, "col_offset": 8, "nodeName": "self", "type": "ShowAndTellModel"}, {"lineNumber": 192, "col_offset": 18, "nodeName": "train_inception", "type": "Any"}, {"lineNumber": 194, "col_offset": 31, "nodeName": "tf", "type": "Any"}, {"lineNumber": 195, "col_offset": 8, "nodeName": "GraphKeys", "type": "Any"}, {"lineNumber": 198, "col_offset": 9, "nodeName": "variable_scope", "type": "Any"}, {"lineNumber": 199, "col_offset": 25, "nodeName": "fully_connected", "type": "Any"}, {"lineNumber": 208, "col_offset": 4, "nodeName": "tf", "type": "Any"}, {"lineNumber": 208, "col_offset": 16, "nodeName": "config", "type": "Any"}, {"lineNumber": 221, "col_offset": 9, "nodeName": "variable_scope", "type": "Any"}, {"lineNumber": 221, "col_offset": 45, "nodeName": "device", "type": "Any"}, {"lineNumber": 222, "col_offset": 22, "nodeName": "get_variable", "type": "Any"}, {"lineNumber": 226, "col_offset": 23, "nodeName": "embedding_lookup", "type": "Any"}, {"lineNumber": 226, "col_offset": 46, "nodeName": "embedding_map", "type": "Any"}, {"lineNumber": 226, "col_offset": 61, "nodeName": "input_seqs", "type": "Any"}, {"lineNumber": 247, "col_offset": 16, "nodeName": "rnn", "type": "Any"}, {"lineNumber": 248, "col_offset": 18, "nodeName": "num_lstm_units", "type": "Any"}, {"lineNumber": 249, "col_offset": 7, "nodeName": "self", "type": "ShowAndTellModel"}, {"lineNumber": 250, "col_offset": 18, "nodeName": "DropoutWrapper", "type": "Any"}, {"lineNumber": 251, "col_offset": 10, "nodeName": "lstm_cell", "type": "Any"}, {"lineNumber": 255, "col_offset": 9, "nodeName": "variable_scope", "type": "Any"}, {"lineNumber": 257, "col_offset": 19, "nodeName": "zero_state", "type": "Any"}, {"lineNumber": 259, "col_offset": 6, "nodeName": "_", "type": "Any"}, {"lineNumber": 259, "col_offset": 9, "nodeName": "initial_state", "type": "Any"}, {"lineNumber": 259, "col_offset": 25, "nodeName": "lstm_cell", "type": "Any"}, {"lineNumber": 259, "col_offset": 35, "nodeName": "image_embeddings", "type": "Any"}, {"lineNumber": 259, "col_offset": 58, "nodeName": "zero_state", "type": "Any"}, {"lineNumber": 262, "col_offset": 6, "nodeName": "reuse_variables", "type": "Any"}, {"lineNumber": 264, "col_offset": 9, "nodeName": "mode", "type": "Any"}, {"lineNumber": 273, "col_offset": 8, "nodeName": "state_tuple", "type": "Any"}, {"lineNumber": 284, "col_offset": 8, "nodeName": "sequence_length", "type": "Any"}, {"lineNumber": 293, "col_offset": 19, "nodeName": "tf", "type": "Any"}, {"lineNumber": 293, "col_offset": 49, "nodeName": "output_size", "type": "Any"}, {"lineNumber": 295, "col_offset": 9, "nodeName": "variable_scope", "type": "Any"}, {"lineNumber": 296, "col_offset": 15, "nodeName": "fully_connected", "type": "Any"}, {"lineNumber": 303, "col_offset": 7, "nodeName": "self", "type": "ShowAndTellModel"}, {"lineNumber": 304, "col_offset": 6, "nodeName": "softmax", "type": "Any"}, {"lineNumber": 304, "col_offset": 20, "nodeName": "logits", "type": "Any"}, {"lineNumber": 306, "col_offset": 16, "nodeName": "reshape", "type": "Any"}, {"lineNumber": 306, "col_offset": 27, "nodeName": "target_seqs", "type": "Any"}, {"lineNumber": 307, "col_offset": 16, "nodeName": "to_float", "type": "Any"}, {"lineNumber": 310, "col_offset": 15, "nodeName": "sparse_softmax_cross_entropy_with_logits", "type": "Any"}, {"lineNumber": 312, "col_offset": 19, "nodeName": "div", "type": "Any"}, {"lineNumber": 315, "col_offset": 6, "nodeName": "add_loss", "type": "Any"}, {"lineNumber": 315, "col_offset": 25, "nodeName": "batch_loss", "type": "Any"}, {"lineNumber": 316, "col_offset": 19, "nodeName": "get_total_loss", "type": "Any"}, {"lineNumber": 319, "col_offset": 6, "nodeName": "scalar", "type": "Any"}, {"lineNumber": 319, "col_offset": 45, "nodeName": "batch_loss", "type": "Any"}, {"lineNumber": 320, "col_offset": 6, "nodeName": "scalar", "type": "Any"}, {"lineNumber": 320, "col_offset": 45, "nodeName": "total_loss", "type": "Any"}, {"lineNumber": 321, "col_offset": 17, "nodeName": "trainable_variables", "type": "Any"}, {"lineNumber": 324, "col_offset": 6, "nodeName": "self", "type": "ShowAndTellModel"}, {"lineNumber": 325, "col_offset": 6, "nodeName": "self", "type": "ShowAndTellModel"}, {"lineNumber": 326, "col_offset": 6, "nodeName": "self", "type": "ShowAndTellModel"}, {"lineNumber": 330, "col_offset": 7, "nodeName": "self", "type": "ShowAndTellModel"}, {"lineNumber": 332, "col_offset": 14, "nodeName": "Saver", "type": "Any"}, {"lineNumber": 332, "col_offset": 29, "nodeName": "inception_variables", "type": "Any"}, {"lineNumber": 339, "col_offset": 6, "nodeName": "self", "type": "ShowAndTellModel"}, {"lineNumber": 343, "col_offset": 18, "nodeName": "tf", "type": "Any"}, {"lineNumber": 353, "col_offset": 4, "nodeName": "self", "type": "ShowAndTellModel"}, {"lineNumber": 354, "col_offset": 4, "nodeName": "self", "type": "ShowAndTellModel"}, {"lineNumber": 355, "col_offset": 4, "nodeName": "self", "type": "ShowAndTellModel"}, {"lineNumber": 356, "col_offset": 4, "nodeName": "self", "type": "ShowAndTellModel"}, {"lineNumber": 357, "col_offset": 4, "nodeName": "self", "type": "ShowAndTellModel"}, {"lineNumber": 358, "col_offset": 4, "nodeName": "self", "type": "ShowAndTellModel"}, {"lineNumber": 60, "col_offset": 16, "nodeName": "initializer_scale", "type": "Any"}, {"lineNumber": 61, "col_offset": 15, "nodeName": "config", "type": "Any"}, {"lineNumber": 115, "col_offset": 54, "nodeName": "is_training", "type": "Callable[[], Any]"}, {"lineNumber": 116, "col_offset": 49, "nodeName": "config", "type": "Any"}, {"lineNumber": 117, "col_offset": 48, "nodeName": "config", "type": "Any"}, {"lineNumber": 119, "col_offset": 55, "nodeName": "config", "type": "Any"}, {"lineNumber": 132, "col_offset": 19, "nodeName": "tf", "type": "Any"}, {"lineNumber": 132, "col_offset": 40, "nodeName": "string", "type": "Any"}, {"lineNumber": 133, "col_offset": 19, "nodeName": "tf", "type": "Any"}, {"lineNumber": 133, "col_offset": 40, "nodeName": "int64", "type": "Any"}, {"lineNumber": 138, "col_offset": 15, "nodeName": "tf", "type": "Any"}, {"lineNumber": 138, "col_offset": 30, "nodeName": "process_image", "type": "Callable[..., Any]"}, {"lineNumber": 138, "col_offset": 49, "nodeName": "image_feed", "type": "Any"}, {"lineNumber": 139, "col_offset": 19, "nodeName": "tf", "type": "Any"}, {"lineNumber": 146, "col_offset": 20, "nodeName": "input_ops", "type": "Any"}, {"lineNumber": 147, "col_offset": 10, "nodeName": "self", "type": "ShowAndTellModel"}, {"lineNumber": 148, "col_offset": 10, "nodeName": "config", "type": "Any"}, {"lineNumber": 150, "col_offset": 21, "nodeName": "batch_size", "type": "Any"}, {"lineNumber": 151, "col_offset": 27, "nodeName": "values_per_input_shard", "type": "Any"}, {"lineNumber": 152, "col_offset": 38, "nodeName": "input_queue_capacity_factor", "type": "Any"}, {"lineNumber": 153, "col_offset": 29, "nodeName": "num_input_reader_threads", "type": "Any"}, {"lineNumber": 157, "col_offset": 13, "nodeName": "num_preprocess_threads", "type": "Any"}, {"lineNumber": 159, "col_offset": 29, "nodeName": "config", "type": "Any"}, {"lineNumber": 160, "col_offset": 38, "nodeName": "dequeue", "type": "Any"}, {"lineNumber": 161, "col_offset": 33, "nodeName": "parse_sequence_example", "type": "Any"}, {"lineNumber": 162, "col_offset": 12, "nodeName": "serialized_sequence_example", "type": "Any"}, {"lineNumber": 165, "col_offset": 16, "nodeName": "process_image", "type": "Callable[..., Any]"}, {"lineNumber": 165, "col_offset": 35, "nodeName": "encoded_image", "type": "Any"}, {"lineNumber": 166, "col_offset": 8, "nodeName": "append", "type": "Callable"}, {"lineNumber": 169, "col_offset": 28, "nodeName": "num_preprocess_threads", "type": "Any"}, {"lineNumber": 170, "col_offset": 24, "nodeName": "config", "type": "Any"}, {"lineNumber": 172, "col_offset": 10, "nodeName": "input_ops", "type": "Any"}, {"lineNumber": 173, "col_offset": 54, "nodeName": "batch_size", "type": "Any"}, {"lineNumber": 174, "col_offset": 58, "nodeName": "queue_capacity", "type": "Any"}, {"lineNumber": 192, "col_offset": 18, "nodeName": "self", "type": "ShowAndTellModel"}, {"lineNumber": 193, "col_offset": 20, "nodeName": "is_training", "type": "Callable[[], Any]"}, {"lineNumber": 195, "col_offset": 8, "nodeName": "tf", "type": "Any"}, {"lineNumber": 198, "col_offset": 9, "nodeName": "tf", "type": "Any"}, {"lineNumber": 199, "col_offset": 25, "nodeName": "layers", "type": "Any"}, {"lineNumber": 200, "col_offset": 17, "nodeName": "inception_output", "type": "Any"}, {"lineNumber": 201, "col_offset": 22, "nodeName": "embedding_size", "type": "Any"}, {"lineNumber": 203, "col_offset": 30, "nodeName": "initializer", "type": "Any"}, {"lineNumber": 205, "col_offset": 16, "nodeName": "scope", "type": "Any"}, {"lineNumber": 208, "col_offset": 16, "nodeName": "self", "type": "ShowAndTellModel"}, {"lineNumber": 221, "col_offset": 9, "nodeName": "tf", "type": "Any"}, {"lineNumber": 221, "col_offset": 45, "nodeName": "tf", "type": "Any"}, {"lineNumber": 222, "col_offset": 22, "nodeName": "tf", "type": "Any"}, {"lineNumber": 225, "col_offset": 22, "nodeName": "initializer", "type": "Any"}, {"lineNumber": 226, "col_offset": 23, "nodeName": "nn", "type": "Any"}, {"lineNumber": 226, "col_offset": 61, "nodeName": "self", "type": "ShowAndTellModel"}, {"lineNumber": 247, "col_offset": 16, "nodeName": "contrib", "type": "Any"}, {"lineNumber": 248, "col_offset": 18, "nodeName": "config", "type": "Any"}, {"lineNumber": 250, "col_offset": 18, "nodeName": "rnn", "type": "Any"}, {"lineNumber": 252, "col_offset": 26, "nodeName": "lstm_dropout_keep_prob", "type": "Any"}, {"lineNumber": 253, "col_offset": 27, "nodeName": "lstm_dropout_keep_prob", "type": "Any"}, {"lineNumber": 255, "col_offset": 9, "nodeName": "tf", "type": "Any"}, {"lineNumber": 255, "col_offset": 47, "nodeName": "initializer", "type": "Any"}, {"lineNumber": 257, "col_offset": 19, "nodeName": "lstm_cell", "type": "Any"}, {"lineNumber": 258, "col_offset": 65, "nodeName": "float32", "type": "Any"}, {"lineNumber": 259, "col_offset": 35, "nodeName": "self", "type": "ShowAndTellModel"}, {"lineNumber": 262, "col_offset": 6, "nodeName": "lstm_scope", "type": "Any"}, {"lineNumber": 264, "col_offset": 9, "nodeName": "self", "type": "ShowAndTellModel"}, {"lineNumber": 267, "col_offset": 8, "nodeName": "concat_v2", "type": "Any"}, {"lineNumber": 267, "col_offset": 21, "nodeName": "initial_state", "type": "Any"}, {"lineNumber": 270, "col_offset": 21, "nodeName": "placeholder", "type": "Any"}, {"lineNumber": 273, "col_offset": 22, "nodeName": "split", "type": "Any"}, {"lineNumber": 276, "col_offset": 36, "nodeName": "lstm_cell", "type": "Any"}, {"lineNumber": 281, "col_offset": 8, "nodeName": "concat_v2", "type": "Any"}, {"lineNumber": 281, "col_offset": 21, "nodeName": "state_tuple", "type": "Any"}, {"lineNumber": 284, "col_offset": 26, "nodeName": "reduce_sum", "type": "Any"}, {"lineNumber": 284, "col_offset": 40, "nodeName": "input_mask", "type": "Any"}, {"lineNumber": 285, "col_offset": 26, "nodeName": "dynamic_rnn", "type": "Any"}, {"lineNumber": 293, "col_offset": 49, "nodeName": "lstm_cell", "type": "Any"}, {"lineNumber": 295, "col_offset": 9, "nodeName": "tf", "type": "Any"}, {"lineNumber": 296, "col_offset": 15, "nodeName": "layers", "type": "Any"}, {"lineNumber": 297, "col_offset": 17, "nodeName": "lstm_outputs", "type": "Any"}, {"lineNumber": 298, "col_offset": 22, "nodeName": "vocab_size", "type": "Any"}, {"lineNumber": 300, "col_offset": 30, "nodeName": "initializer", "type": "Any"}, {"lineNumber": 301, "col_offset": 16, "nodeName": "logits_scope", "type": "Any"}, {"lineNumber": 304, "col_offset": 6, "nodeName": "nn", "type": "Any"}, {"lineNumber": 306, "col_offset": 16, "nodeName": "tf", "type": "Any"}, {"lineNumber": 306, "col_offset": 27, "nodeName": "self", "type": "ShowAndTellModel"}, {"lineNumber": 307, "col_offset": 16, "nodeName": "tf", "type": "Any"}, {"lineNumber": 307, "col_offset": 28, "nodeName": "reshape", "type": "Any"}, {"lineNumber": 307, "col_offset": 39, "nodeName": "input_mask", "type": "Any"}, {"lineNumber": 310, "col_offset": 15, "nodeName": "nn", "type": "Any"}, {"lineNumber": 310, "col_offset": 69, "nodeName": "targets", "type": "Any"}, {"lineNumber": 311, "col_offset": 69, "nodeName": "logits", "type": "Any"}, {"lineNumber": 312, "col_offset": 19, "nodeName": "tf", "type": "Any"}, {"lineNumber": 312, "col_offset": 26, "nodeName": "reduce_sum", "type": "Any"}, {"lineNumber": 313, "col_offset": 26, "nodeName": "reduce_sum", "type": "Any"}, {"lineNumber": 313, "col_offset": 40, "nodeName": "weights", "type": "Any"}, {"lineNumber": 315, "col_offset": 6, "nodeName": "losses", "type": "Any"}, {"lineNumber": 316, "col_offset": 19, "nodeName": "losses", "type": "Any"}, {"lineNumber": 319, "col_offset": 6, "nodeName": "summary", "type": "Any"}, {"lineNumber": 320, "col_offset": 6, "nodeName": "summary", "type": "Any"}, {"lineNumber": 321, "col_offset": 17, "nodeName": "tf", "type": "Any"}, {"lineNumber": 322, "col_offset": 8, "nodeName": "histogram", "type": "Any"}, {"lineNumber": 322, "col_offset": 58, "nodeName": "var", "type": "Any"}, {"lineNumber": 332, "col_offset": 14, "nodeName": "train", "type": "Any"}, {"lineNumber": 332, "col_offset": 29, "nodeName": "self", "type": "ShowAndTellModel"}, {"lineNumber": 335, "col_offset": 8, "nodeName": "info", "type": "Any"}, {"lineNumber": 336, "col_offset": 24, "nodeName": "inception_checkpoint_file", "type": "Any"}, {"lineNumber": 337, "col_offset": 8, "nodeName": "restore", "type": "Any"}, {"lineNumber": 337, "col_offset": 22, "nodeName": "sess", "type": "Any"}, {"lineNumber": 337, "col_offset": 28, "nodeName": "inception_checkpoint_file", "type": "Any"}, {"lineNumber": 347, "col_offset": 21, "nodeName": "GLOBAL_STEP", "type": "Any"}, {"lineNumber": 347, "col_offset": 47, "nodeName": "GLOBAL_VARIABLES", "type": "Any"}, {"lineNumber": 60, "col_offset": 16, "nodeName": "config", "type": "Any"}, {"lineNumber": 61, "col_offset": 15, "nodeName": "self", "type": "ShowAndTellModel"}, {"lineNumber": 115, "col_offset": 54, "nodeName": "self", "type": "ShowAndTellModel"}, {"lineNumber": 116, "col_offset": 49, "nodeName": "self", "type": "ShowAndTellModel"}, {"lineNumber": 117, "col_offset": 48, "nodeName": "self", "type": "ShowAndTellModel"}, {"lineNumber": 119, "col_offset": 55, "nodeName": "self", "type": "ShowAndTellModel"}, {"lineNumber": 132, "col_offset": 40, "nodeName": "tf", "type": "Any"}, {"lineNumber": 133, "col_offset": 40, "nodeName": "tf", "type": "Any"}, {"lineNumber": 138, "col_offset": 30, "nodeName": "self", "type": "ShowAndTellModel"}, {"lineNumber": 148, "col_offset": 10, "nodeName": "self", "type": "ShowAndTellModel"}, {"lineNumber": 149, "col_offset": 22, "nodeName": "is_training", "type": "Callable[[], Any]"}, {"lineNumber": 150, "col_offset": 21, "nodeName": "config", "type": "Any"}, {"lineNumber": 151, "col_offset": 27, "nodeName": "config", "type": "Any"}, {"lineNumber": 152, "col_offset": 38, "nodeName": "config", "type": "Any"}, {"lineNumber": 153, "col_offset": 29, "nodeName": "config", "type": "Any"}, {"lineNumber": 157, "col_offset": 13, "nodeName": "config", "type": "Any"}, {"lineNumber": 159, "col_offset": 29, "nodeName": "self", "type": "ShowAndTellModel"}, {"lineNumber": 160, "col_offset": 38, "nodeName": "input_queue", "type": "Any"}, {"lineNumber": 161, "col_offset": 33, "nodeName": "input_ops", "type": "Any"}, {"lineNumber": 163, "col_offset": 26, "nodeName": "image_feature_name", "type": "Any"}, {"lineNumber": 164, "col_offset": 28, "nodeName": "caption_feature_name", "type": "Any"}, {"lineNumber": 165, "col_offset": 16, "nodeName": "self", "type": "ShowAndTellModel"}, {"lineNumber": 165, "col_offset": 60, "nodeName": "thread_id", "type": "int"}, {"lineNumber": 166, "col_offset": 8, "nodeName": "images_and_captions", "type": "List[List[Any]]"}, {"lineNumber": 166, "col_offset": 36, "nodeName": "image", "type": "Any"}, {"lineNumber": 166, "col_offset": 43, "nodeName": "caption", "type": "Any"}, {"lineNumber": 169, "col_offset": 28, "nodeName": "config", "type": "Any"}, {"lineNumber": 170, "col_offset": 24, "nodeName": "self", "type": "ShowAndTellModel"}, {"lineNumber": 173, "col_offset": 54, "nodeName": "config", "type": "Any"}, {"lineNumber": 193, "col_offset": 20, "nodeName": "self", "type": "ShowAndTellModel"}, {"lineNumber": 199, "col_offset": 25, "nodeName": "contrib", "type": "Any"}, {"lineNumber": 201, "col_offset": 22, "nodeName": "config", "type": "Any"}, {"lineNumber": 203, "col_offset": 30, "nodeName": "self", "type": "ShowAndTellModel"}, {"lineNumber": 224, "col_offset": 17, "nodeName": "vocab_size", "type": "Any"}, {"lineNumber": 224, "col_offset": 41, "nodeName": "embedding_size", "type": "Any"}, {"lineNumber": 225, "col_offset": 22, "nodeName": "self", "type": "ShowAndTellModel"}, {"lineNumber": 226, "col_offset": 23, "nodeName": "tf", "type": "Any"}, {"lineNumber": 247, "col_offset": 16, "nodeName": "tf", "type": "Any"}, {"lineNumber": 248, "col_offset": 18, "nodeName": "self", "type": "ShowAndTellModel"}, {"lineNumber": 250, "col_offset": 18, "nodeName": "contrib", "type": "Any"}, {"lineNumber": 252, "col_offset": 26, "nodeName": "config", "type": "Any"}, {"lineNumber": 253, "col_offset": 27, "nodeName": "config", "type": "Any"}, {"lineNumber": 255, "col_offset": 47, "nodeName": "self", "type": "ShowAndTellModel"}, {"lineNumber": 258, "col_offset": 65, "nodeName": "tf", "type": "Any"}, {"lineNumber": 267, "col_offset": 8, "nodeName": "tf", "type": "Any"}, {"lineNumber": 270, "col_offset": 21, "nodeName": "tf", "type": "Any"}, {"lineNumber": 270, "col_offset": 42, "nodeName": "float32", "type": "Any"}, {"lineNumber": 273, "col_offset": 22, "nodeName": "tf", "type": "Any"}, {"lineNumber": 273, "col_offset": 37, "nodeName": "state_feed", "type": "Any"}, {"lineNumber": 278, "col_offset": 18, "nodeName": "state_tuple", "type": "Any"}, {"lineNumber": 281, "col_offset": 8, "nodeName": "tf", "type": "Any"}, {"lineNumber": 284, "col_offset": 26, "nodeName": "tf", "type": "Any"}, {"lineNumber": 284, "col_offset": 40, "nodeName": "self", "type": "ShowAndTellModel"}, {"lineNumber": 285, "col_offset": 26, "nodeName": "nn", "type": "Any"}, {"lineNumber": 285, "col_offset": 49, "nodeName": "lstm_cell", "type": "Any"}, {"lineNumber": 286, "col_offset": 51, "nodeName": "seq_embeddings", "type": "Any"}, {"lineNumber": 287, "col_offset": 60, "nodeName": "sequence_length", "type": "Any"}, {"lineNumber": 288, "col_offset": 58, "nodeName": "initial_state", "type": "Any"}, {"lineNumber": 289, "col_offset": 50, "nodeName": "float32", "type": "Any"}, {"lineNumber": 290, "col_offset": 50, "nodeName": "lstm_scope", "type": "Any"}, {"lineNumber": 296, "col_offset": 15, "nodeName": "contrib", "type": "Any"}, {"lineNumber": 298, "col_offset": 22, "nodeName": "config", "type": "Any"}, {"lineNumber": 300, "col_offset": 30, "nodeName": "self", "type": "ShowAndTellModel"}, {"lineNumber": 304, "col_offset": 6, "nodeName": "tf", "type": "Any"}, {"lineNumber": 307, "col_offset": 28, "nodeName": "tf", "type": "Any"}, {"lineNumber": 307, "col_offset": 39, "nodeName": "self", "type": "ShowAndTellModel"}, {"lineNumber": 310, "col_offset": 15, "nodeName": "tf", "type": "Any"}, {"lineNumber": 312, "col_offset": 26, "nodeName": "tf", "type": "Any"}, {"lineNumber": 312, "col_offset": 40, "nodeName": "multiply", "type": "Any"}, {"lineNumber": 312, "col_offset": 52, "nodeName": "losses", "type": "Any"}, {"lineNumber": 312, "col_offset": 60, "nodeName": "weights", "type": "Any"}, {"lineNumber": 313, "col_offset": 26, "nodeName": "tf", "type": "Any"}, {"lineNumber": 315, "col_offset": 6, "nodeName": "tf", "type": "Any"}, {"lineNumber": 316, "col_offset": 19, "nodeName": "tf", "type": "Any"}, {"lineNumber": 319, "col_offset": 6, "nodeName": "tf", "type": "Any"}, {"lineNumber": 320, "col_offset": 6, "nodeName": "tf", "type": "Any"}, {"lineNumber": 322, "col_offset": 8, "nodeName": "summary", "type": "Any"}, {"lineNumber": 322, "col_offset": 45, "nodeName": "name", "type": "Any"}, {"lineNumber": 332, "col_offset": 14, "nodeName": "tf", "type": "Any"}, {"lineNumber": 335, "col_offset": 8, "nodeName": "logging", "type": "Any"}, {"lineNumber": 336, "col_offset": 24, "nodeName": "config", "type": "Any"}, {"lineNumber": 337, "col_offset": 8, "nodeName": "saver", "type": "Any"}, {"lineNumber": 337, "col_offset": 28, "nodeName": "config", "type": "Any"}, {"lineNumber": 347, "col_offset": 21, "nodeName": "GraphKeys", "type": "Any"}, {"lineNumber": 347, "col_offset": 47, "nodeName": "GraphKeys", "type": "Any"}, {"lineNumber": 60, "col_offset": 16, "nodeName": "self", "type": "ShowAndTellModel"}, {"lineNumber": 149, "col_offset": 22, "nodeName": "self", "type": "ShowAndTellModel"}, {"lineNumber": 150, "col_offset": 21, "nodeName": "self", "type": "ShowAndTellModel"}, {"lineNumber": 151, "col_offset": 27, "nodeName": "self", "type": "ShowAndTellModel"}, {"lineNumber": 152, "col_offset": 38, "nodeName": "self", "type": "ShowAndTellModel"}, {"lineNumber": 153, "col_offset": 29, "nodeName": "self", "type": "ShowAndTellModel"}, {"lineNumber": 157, "col_offset": 13, "nodeName": "self", "type": "ShowAndTellModel"}, {"lineNumber": 163, "col_offset": 26, "nodeName": "config", "type": "Any"}, {"lineNumber": 164, "col_offset": 28, "nodeName": "config", "type": "Any"}, {"lineNumber": 169, "col_offset": 28, "nodeName": "self", "type": "ShowAndTellModel"}, {"lineNumber": 173, "col_offset": 54, "nodeName": "self", "type": "ShowAndTellModel"}, {"lineNumber": 199, "col_offset": 25, "nodeName": "tf", "type": "Any"}, {"lineNumber": 201, "col_offset": 22, "nodeName": "self", "type": "ShowAndTellModel"}, {"lineNumber": 224, "col_offset": 17, "nodeName": "config", "type": "Any"}, {"lineNumber": 224, "col_offset": 41, "nodeName": "config", "type": "Any"}, {"lineNumber": 250, "col_offset": 18, "nodeName": "tf", "type": "Any"}, {"lineNumber": 252, "col_offset": 26, "nodeName": "self", "type": "ShowAndTellModel"}, {"lineNumber": 253, "col_offset": 27, "nodeName": "self", "type": "ShowAndTellModel"}, {"lineNumber": 258, "col_offset": 21, "nodeName": "get_shape", "type": "Any"}, {"lineNumber": 270, "col_offset": 42, "nodeName": "tf", "type": "Any"}, {"lineNumber": 277, "col_offset": 19, "nodeName": "squeeze", "type": "Any"}, {"lineNumber": 277, "col_offset": 30, "nodeName": "seq_embeddings", "type": "Any"}, {"lineNumber": 285, "col_offset": 26, "nodeName": "tf", "type": "Any"}, {"lineNumber": 286, "col_offset": 51, "nodeName": "self", "type": "ShowAndTellModel"}, {"lineNumber": 289, "col_offset": 50, "nodeName": "tf", "type": "Any"}, {"lineNumber": 296, "col_offset": 15, "nodeName": "tf", "type": "Any"}, {"lineNumber": 298, "col_offset": 22, "nodeName": "self", "type": "ShowAndTellModel"}, {"lineNumber": 312, "col_offset": 40, "nodeName": "tf", "type": "Any"}, {"lineNumber": 322, "col_offset": 8, "nodeName": "tf", "type": "Any"}, {"lineNumber": 322, "col_offset": 45, "nodeName": "op", "type": "Any"}, {"lineNumber": 335, "col_offset": 8, "nodeName": "tf", "type": "Any"}, {"lineNumber": 336, "col_offset": 24, "nodeName": "self", "type": "ShowAndTellModel"}, {"lineNumber": 337, "col_offset": 28, "nodeName": "self", "type": "ShowAndTellModel"}, {"lineNumber": 347, "col_offset": 21, "nodeName": "tf", "type": "Any"}, {"lineNumber": 347, "col_offset": 47, "nodeName": "tf", "type": "Any"}, {"lineNumber": 163, "col_offset": 26, "nodeName": "self", "type": "ShowAndTellModel"}, {"lineNumber": 164, "col_offset": 28, "nodeName": "self", "type": "ShowAndTellModel"}, {"lineNumber": 224, "col_offset": 17, "nodeName": "self", "type": "ShowAndTellModel"}, {"lineNumber": 224, "col_offset": 41, "nodeName": "self", "type": "ShowAndTellModel"}, {"lineNumber": 258, "col_offset": 21, "nodeName": "image_embeddings", "type": "Any"}, {"lineNumber": 271, "col_offset": 49, "nodeName": "sum", "type": "Callable"}, {"lineNumber": 271, "col_offset": 53, "nodeName": "state_size", "type": "Any"}, {"lineNumber": 277, "col_offset": 19, "nodeName": "tf", "type": "Any"}, {"lineNumber": 277, "col_offset": 30, "nodeName": "self", "type": "ShowAndTellModel"}, {"lineNumber": 322, "col_offset": 45, "nodeName": "var", "type": "Any"}, {"lineNumber": 258, "col_offset": 21, "nodeName": "self", "type": "ShowAndTellModel"}, {"lineNumber": 271, "col_offset": 53, "nodeName": "lstm_cell", "type": "Any"}]